googleapiwrapper/__init__.py
googleapiwrapper/googledrivewrapper.py
googleapiwrapper/googleemailwrapper.py
googleapiwrapper-0.2.0.dist-info/WHEEL
googleapiwrapper-0.2.0.dist-info/METADATA
googleapiwrapper-0.2.0.dist-info/RECORD
