Metadata-Version: 2.1
Name: googleapiwrapper
Version: 0.2.0
Summary: A simple wrapper for GoogleApi 
Home-page: https://github.com/wmmak12/googleapiwrapper
License: MIT
Keywords: google,api
Author: ethan mak
Author-email: wmmak8@gmail.com
Requires-Python: >=3.7,<4.0
Classifier: License :: OSI Approved :: MIT License
Classifier: Programming Language :: Python :: 3
Classifier: Programming Language :: Python :: 3.7
Classifier: Programming Language :: Python :: 3.8
Requires-Dist: google-api-python-client (>=1.8.0,<2.0.0)
Project-URL: Repository, https://github.com/wmmak12/googleapiwrapper
